django_marketing_redirects/__init__.py
django_marketing_redirects/middleware.py
django_marketing_redirects/models.py
django_marketing_redirects/migrations/0001_initial.py
django_marketing_redirects/migrations/__init__.py
django_marketing_redirects-0.9.0.dist-info/DESCRIPTION.rst
django_marketing_redirects-0.9.0.dist-info/METADATA
django_marketing_redirects-0.9.0.dist-info/RECORD
django_marketing_redirects-0.9.0.dist-info/WHEEL
django_marketing_redirects-0.9.0.dist-info/metadata.json
django_marketing_redirects-0.9.0.dist-info/top_level.txt
tests/__init__.py
tests/settings.py
tests/test_middleware.py
tests/test_middleware_base_functionality.py
tests/test_models.py
tests/urls.py
