Metadata-Version: 2.0
Name: django-marketing-redirects
Version: 0.9.0
Summary: Redirect URLs including query parameters necessary for marketing use.
Home-page: https://github.com/seawolf42/django-marketing-redirects
Author: jeffrey k eliasen
Author-email: jeff+django-marketing-redirects@jke.net
License: BSD License
Keywords: django-marketing-redirects
Platform: UNKNOWN
Classifier: Framework :: Django
Classifier: Framework :: Django :: 1.8
Classifier: Framework :: Django :: 1.9
Classifier: Framework :: Django :: 1.10
Classifier: Framework :: Django :: 1.11
Classifier: Framework :: Django :: 2.0
Classifier: Intended Audience :: Developers
Classifier: License :: OSI Approved :: BSD License
Classifier: Natural Language :: English
Classifier: Programming Language :: Python :: 2
Classifier: Programming Language :: Python :: 2.7
Classifier: Programming Language :: Python :: 3
Classifier: Programming Language :: Python :: 3.5
Classifier: Programming Language :: Python :: 3.6
Requires-Dist: Django (>=1.8)
